src/__init__.py
src/core.py
src/interactive.py
src/main.py
src/ray.py
src/util.py
wptc-1.0.5.dist-info/licenses/LICENSE
wptc-1.0.5.dist-info/METADATA
wptc-1.0.5.dist-info/WHEEL
wptc-1.0.5.dist-info/entry_points.txt
wptc-1.0.5.dist-info/top_level.txt
wptc-1.0.5.dist-info/RECORD
